docs/clean_sphinx_docs.py
docs/source/conf.py
scripts/setup_dev.py
scripts/validate_code.py
twin4build/__init__.py
twin4build/core/__init__.py
twin4build/estimator/__init__.py
twin4build/estimator/estimator.py
twin4build/examples/__init__.py
twin4build/examples/mortar.py
twin4build/examples/optimizer_doc.py
twin4build/examples/utils.py
twin4build/examples/estimator_example/__init__.py
twin4build/examples/estimator_example/co2_sensor.csv
twin4build/examples/estimator_example/damper_position_sensor.csv
twin4build/examples/estimator_example/one_room_example_model.xlsm
twin4build/examples/estimator_example/outdoor_environment.csv
twin4build/examples/estimator_example/semantic_model.ttl
twin4build/examples/estimator_example/supply_air_temperature.csv
twin4build/examples/estimator_example/temperature_heating_setpoint.csv
twin4build/examples/estimator_example/temperature_sensor.csv
twin4build/examples/estimator_example/valve_position_sensor.csv
twin4build/examples/neural_policy_controller_example/__init__.py
twin4build/examples/neural_policy_controller_example/neural_policy_example.py
twin4build/model/__init__.py
twin4build/model/model.py
twin4build/model/semantic_model/__init__.py
twin4build/model/semantic_model/semantic_model.py
twin4build/model/semantic_model/mappings/AirToAirHeatRecovery.yml
twin4build/model/semantic_model/mappings/BuildingSpace.yml
twin4build/model/semantic_model/mappings/Coil.yml
twin4build/model/semantic_model/mappings/Damper.yml
twin4build/model/semantic_model/mappings/Fan.yml
twin4build/model/semantic_model/mappings/FlowJunction.yml
twin4build/model/semantic_model/mappings/Meter.yml
twin4build/model/semantic_model/mappings/Property.yml
twin4build/model/semantic_model/mappings/Pump.yml
twin4build/model/semantic_model/mappings/RulebasedController.yml
twin4build/model/semantic_model/mappings/Schedule.yml
twin4build/model/semantic_model/mappings/Sensor.yml
twin4build/model/semantic_model/mappings/SetpointController.yml
twin4build-1.1.1.dist-info/licenses/LICENSE.txt
twin4build-1.1.1.dist-info/METADATA
twin4build-1.1.1.dist-info/WHEEL
twin4build-1.1.1.dist-info/top_level.txt
twin4build-1.1.1.dist-info/RECORD
