Metadata-Version: 2.4
Name: twin4build
Version: 1.1.1
Summary: Dynamic simulation of buildings and integration with semantic modeling.
Author-email: Jakob Bjørnskov <jakob.bjornskov@gmail.com>
License-Expression: MIT
Project-URL: homepage, https://github.com/JBjoernskov/Twin4Build/
Project-URL: documentation, https://twin4build.readthedocs.io/
Project-URL: repository, https://github.com/JBjoernskov/Twin4Build/
Keywords: Digital Twins,Building Performance Simulation,Semantic Modeling,Energy Modeling
Classifier: Programming Language :: Python :: 3.9
Classifier: Programming Language :: Python :: 3.10
Classifier: Programming Language :: Python :: 3.11
Classifier: Programming Language :: Python :: 3.12
Classifier: Topic :: Scientific/Engineering :: Artificial Intelligence
Classifier: Topic :: Scientific/Engineering :: Physics
Requires-Python: >=3.9
License-File: LICENSE.txt
Requires-Dist: matplotlib
Requires-Dist: seaborn
Requires-Dist: pandas
Requires-Dist: torch
Requires-Dist: pydot<=2.0.0
Requires-Dist: tqdm
Requires-Dist: fmpy
Requires-Dist: scipy
Requires-Dist: numpy
Requires-Dist: prettytable
Requires-Dist: jupyter
Requires-Dist: nbformat
Requires-Dist: rdflib
Requires-Dist: brickschema[persistence]
Requires-Dist: click_spinner
Requires-Dist: xlrd
Requires-Dist: rdflib_sqlalchemy
Requires-Dist: pydotplus
Requires-Dist: typer
Requires-Dist: openpyxl
Requires-Dist: psycopg2
Requires-Dist: pyarrow
Requires-Dist: beautifulsoup4
Requires-Dist: python-dateutil
Requires-Dist: pathlib
Provides-Extra: dev
Requires-Dist: coverage; extra == "dev"
Requires-Dist: black; extra == "dev"
Requires-Dist: flake8; extra == "dev"
Requires-Dist: isort; extra == "dev"
Requires-Dist: sphinx; extra == "dev"
Requires-Dist: sphinx-rtd-theme; extra == "dev"
Requires-Dist: sphinx-autodoc-typehints; extra == "dev"
Requires-Dist: myst-parser; extra == "dev"
Requires-Dist: twine; extra == "dev"
Provides-Extra: database
Requires-Dist: psycopg2-binary; extra == "database"
Requires-Dist: sqlalchemy; extra == "database"
Provides-Extra: all
Requires-Dist: coverage; extra == "all"
Requires-Dist: black; extra == "all"
Requires-Dist: flake8; extra == "all"
Requires-Dist: isort; extra == "all"
Requires-Dist: sphinx; extra == "all"
Requires-Dist: sphinx-rtd-theme; extra == "all"
Requires-Dist: sphinx-autodoc-typehints; extra == "all"
Requires-Dist: myst-parser; extra == "all"
Requires-Dist: psycopg2-binary; extra == "all"
Requires-Dist: sqlalchemy; extra == "all"
Requires-Dist: twine; extra == "all"
Dynamic: license-file
